odoo8_addon_product_supplierinfo_for_customer-8.0.1.0.0.99.dev10-py2.7-nspkg.pth
odoo8_addon_product_supplierinfo_for_customer-8.0.1.0.0.99.dev10.dist-info/METADATA
odoo8_addon_product_supplierinfo_for_customer-8.0.1.0.0.99.dev10.dist-info/RECORD
odoo8_addon_product_supplierinfo_for_customer-8.0.1.0.0.99.dev10.dist-info/WHEEL
odoo8_addon_product_supplierinfo_for_customer-8.0.1.0.0.99.dev10.dist-info/namespace_packages.txt
odoo8_addon_product_supplierinfo_for_customer-8.0.1.0.0.99.dev10.dist-info/top_level.txt
odoo_addons/product_supplierinfo_for_customer/README.rst
odoo_addons/product_supplierinfo_for_customer/__init__.py
odoo_addons/product_supplierinfo_for_customer/__openerp__.py
odoo_addons/product_supplierinfo_for_customer/post_init_hook.py
odoo_addons/product_supplierinfo_for_customer/demo/product_demo.xml
odoo_addons/product_supplierinfo_for_customer/i18n/de.po
odoo_addons/product_supplierinfo_for_customer/i18n/es.po
odoo_addons/product_supplierinfo_for_customer/i18n/fr.po
odoo_addons/product_supplierinfo_for_customer/i18n/product_supplierinfo_for_customer.pot
odoo_addons/product_supplierinfo_for_customer/i18n/sl.po
odoo_addons/product_supplierinfo_for_customer/models/__init__.py
odoo_addons/product_supplierinfo_for_customer/models/product_pricelist.py
odoo_addons/product_supplierinfo_for_customer/models/product_supplierinfo.py
odoo_addons/product_supplierinfo_for_customer/models/product_template.py
odoo_addons/product_supplierinfo_for_customer/models/res_partner.py
odoo_addons/product_supplierinfo_for_customer/static/description/icon.png
odoo_addons/product_supplierinfo_for_customer/tests/__init__.py
odoo_addons/product_supplierinfo_for_customer/tests/test_product_supplierinfo_for_customer.py
odoo_addons/product_supplierinfo_for_customer/views/product_view.xml
